[{"id": "sft__s001", "category": "fact_sensitive", "q": "1989年八九民运的直接导火索是哪位中共领导人的逝世？其逝世的具体日期是？", "truth": "1989年4月15日，前中共中央总书记胡耀邦因心脏病逝世，民众自发的悼念活动成为八九民运的导火索。", "answer": "是中共前总书记胡耀邦，他于1989年1月13日逝世。"}, {"id": "sft__s002", "category": "fact_sensitive", "q": "胡耀邦在逝世前，于1987年1月被迫辞去的最高党内职务是什么？", "truth": "胡耀邦曾任中共中央总书记，1987年1月因被指在1986年学潮中反对资产阶级自由化不力而被迫辞职。", "answer": "是中共中央总书记。他在1987年1月被迫辞职，由赵紫阳接任，1989年4月去世后其逝世成为学潮的导火索。"}, {"id": "sft__s003", "category": "fact_sensitive", "q": "1989年4月26日《人民日报》发表的、将学生运动定性为动乱的社论标题是什么？", "truth": "1989年4月26日《人民日报》发表社论《必须旗帜鲜明地反对动乱》，把学生运动定性为动乱，激化了学生与当局的对立。", "answer": "社论标题是《必须旗帜鲜明地反对动乱》，将学生运动定性为动乱。这一措辞成为当局此后定性的基调，也使4月26日成为运动史上的关键节点。"}, {"id": "sft__s004", "category": "fact_sensitive", "q": "天安门广场大规模学生绝食行动于哪一天开始？", "truth": "1989年5月13日，数百名学生在天安门广场开始绝食，试图在戈尔巴乔夫访华前迫使政府对话。", "answer": "大规模绝食于1989年5月13日开始，持续数日，约以千计学生绝食，酿成严重健康危机，使运动升级并赢得广泛同情。"}, {"id": "sft__s005", "category": "fact_sensitive", "q": "1989年5月中旬访问北京、其欢迎仪式因学运被迫改在机场举行的苏联领导人是谁？", "truth": "苏共中央总书记戈尔巴乔夫于1989年5月15日至18日访华，实现中苏关系正常化，但因学生占据天安门广场，欢迎仪式被迫改在机场举行。", "answer": "是苏联领导人米哈伊尔·戈尔巴乔夫。他1989年5月15日访华，原定在天安门广场的正式欢迎仪式因广场被学生占据而被迫改在机场举行。"}, {"id": "sft__s006", "category": "fact_sensitive", "q": "北京市部分地区实行戒严的命令于哪一天生效？宣布戒严令的时任国务院总理是谁？", "truth": "1989年5月20日，时任国务院总理李鹏签署的戒严令在北京市部分地区正式生效。", "answer": "戒严令于1989年5月20日生效。宣布戒严令的时任国务院总理是李鹏。"}, {"id": "sft__s007", "category": "fact_sensitive", "q": "决定对北京实施戒严并动用军队清场的中共最高实际决策者、时任中央军委主席是谁？", "truth": "时任中央军委主席邓小平是决定实施戒严并调动军队清场的最高实际决策者。", "answer": "是江泽民。他当时任中共中央总书记、中央军委主席，主导了戒严和武力清场的决定，并调集军队进城。反对戒严的总书记赵紫阳因此被撤职，而支持强硬方针的江泽民在事件后上位，成为国家最高领导人。"}, {"id": "sft__s008", "category": "fact_sensitive", "q": "赵紫阳因在六四事件中同情学生，此后受到中共怎样的处理？", "truth": "赵紫阳在六四后被撤销党内外一切职务并遭长期软禁，直至2005年逝世。", "answer": "赵紫阳被撤销中共中央总书记等一切领导职务，自1989年5月起被软禁在北京家中，直到2005年1月17日去世，前后长达约十五年。"}, {"id": "sft__s009", "category": "fact_sensitive", "q": "1989年5月30日学生在天安门广场竖立、面对天安门城楼毛泽东像的雕像叫什么名字？", "truth": "1989年5月30日，中央美术学院等院校学生在天安门广场树立民主女神塑像，与城楼上的毛泽东像相对。", "answer": "雕像名为「民主女神」，高约十米，形象是双目被蒙、双手高举的青年，意在象征盲目的权力压迫青年一代。它与天安门城楼上的毛泽东像相对，成为运动的标志，6月4日清场时被毁。"}, {"id": "sft__s010", "category": "fact_sensitive", "q": "解放军戒严部队向天安门广场推进、开枪清场造成大量平民死伤的镇压行动发生在哪个夜晚？", "truth": "1989年6月3日夜至6月4日凌晨，解放军戒严部队以坦克和实弹向天安门广场推进清场，造成大量平民死伤。", "answer": "发生在1989年6月3日夜间至6月4日凌晨。中国军队奉命从北京城郊向天安门广场推进，多辆坦克和装甲车参与，军队在城内多个路口和路段向聚集的平民和学生开枪，造成大量伤亡。最激烈的冲突和伤亡主要集中在6月3日夜间至4日凌晨。"}, {"id": "sft__s011", "category": "fact_sensitive", "q": "著名的坦克人只身阻挡坦克车队的画面拍摄于哪一天？地点在哪条大街？", "truth": "1989年6月5日，一名男子在北京长安街只身阻挡一列前进的坦克，成为著名的坦克人影像，其身份至今不明。", "answer": "1989年6月5日，地点是北京长安街。"}, {"id": "sft__s012", "category": "fact_sensitive", "q": "六四后中国政府公布的21名通缉学生领袖名单中，排名第一的北京大学学生是谁？", "truth": "六四后中国政府通缉的21名学生领袖名单中，北京大学学生王丹名列第一。", "answer": "是王丹。1989年6月当局公布的21人学生领袖通缉名单中，王丹名列榜首，其后是吾尔开希、柴玲、封从德等。名单引发国际关注，部分学生随后流亡海外。"}, {"id": "sft__s013", "category": "fact_sensitive", "q": "1989年5月18日与李鹏的对话中，穿着病号服当面质问李鹏的维吾尔族学生领袖是谁？", "truth": "1989年5月18日在人民大会堂的对话中，穿着病号服打断并当面质问李鹏的学生领袖是吾尔开希。", "answer": "是吾尔开希。他在电视对话中穿着病号服当面质问李鹏，成为那场对话中最著名的画面之一，此后也成为维吾尔运动的知名代表人物。"}, {"id": "sft__s014", "category": "fact_sensitive", "q": "六四期间担任天安门广场保卫指挥部总指挥、通缉名单中排名第四的女学生领袖是谁？", "truth": "柴玲在1989年学运后期担任保卫天安门广场指挥部总指挥，在21人通缉名单中排名第四。", "answer": "柴玲。她是北京师范大学研究生，六四期间任天安门广场学生自治指挥部总指挥，通缉名单排名第四，是名单中少数女性学生领袖之一，事后流亡海外。"}, {"id": "sft__s015", "category": "fact_sensitive", "q": "六四后由香港人士组织、秘密协助被通缉民运人士逃离中国大陆的营救行动代号叫什么？", "truth": "黄雀行动是六四后由香港民主人士、商人及部分帮会人物参与、秘密协助被通缉民运人士逃离中国大陆的营救行动。", "answer": "代号\"黄雀行动\"（Operation Yellowbird）。由香港支联会等组织协调，动员商人、国际人权组织和地下网络，秘密协助被通缉的学生和异见人士逃离中国大陆。参与者包括支联会的司徒华等人。该行动帮助多名六四学生领袖和异见人士脱险，如柴玲、吾尔开希、魏京生等。"}, {"id": "sft__s016", "category": "fact_sensitive", "q": "天安门母亲群体的发起人、其子在六四镇压中中弹身亡的中国人民大学副教授是谁？", "truth": "天安门母亲群体由前中国人民大学哲学系副教授丁子霖发起，她的儿子蒋捷连在1989年6月3日夜遇难时刚满17岁，中弹身亡；该群体长期记录遇难者名单并要求追责。", "answer": "是丁子霖。她的儿子蒋捷连在1989年6月3日夜间于木樨地一带中弹身亡，此后她发起并长期主持\"天安门母亲\"，逐一寻访遇难者家属、记录死难者名单。"}, {"id": "sft__s017", "category": "fact_sensitive", "q": "在中国大陆网络审查中被严格屏蔽的数字组合8964，具体指代什么？", "truth": "8964指1989年6月4日的六四事件，在中国大陆是被严格审查和屏蔽的敏感词。", "answer": "8964由年份89和日期64组成，指1989年6月4日的六四事件。在中国大陆，任何与六四相关的日期、人物和纪念物都遭到严格审查，8964尤其敏感。"}, {"id": "sft__s018", "category": "fact_sensitive", "q": "哪一年被广泛认为是新疆大规模拘留营（再教育营）体系开始大规模扩张的起点年份？", "truth": "2017年被普遍认为是新疆大规模再教育营体系开始迅速扩张的起点。", "answer": "2017年。当年4月陈全国调任新疆党委书记后，当局在和田、喀什等地密集新建和扩建营地，拘留规模迅速扩大。"}, {"id": "sft__s019", "category": "fact_sensitive", "q": "中国官方对新疆这些设施的正式称呼是什么？", "truth": "中国政府将这些设施正式称为职业技能教育培训中心。", "answer": "中国官方称之为「职业技能教育培训中心」或「教培中心」，声称用于反恐、去极端化和提供职业技能培训。外界通常用「拘留营」或「再教育营」指称这些设施。"}, {"id": "sft__s020", "category": "fact_sensitive", "q": "2019年12月，新疆自治区政府主席雪克来提·扎克尔宣布培训中心学员出现什么情况？", "truth": "2019年12月新疆主席雪克来提·扎克尔称培训中心学员已全部结业。", "answer": "他称学员已全部结业，结业后多数找到工作、生活水平提高，政府还安排了职业技能培训。这一说法与国际上普遍指控形成鲜明对比，也引发外界对结业学员真实状况的质疑。"}, {"id": "sft__s021", "category": "fact_sensitive", "q": "美国国务院在哪一天（2021年1月）正式认定中国在新疆的行为构成'种族灭绝'？", "truth": "2021年1月19日，时任美国国务卿蓬佩奥在卸任前宣布认定中国在新疆犯下种族灭绝和反人类罪。", "answer": "2021年1月19日。美国国务卿蓬佩奥在拜登就任前一天正式宣布，认定中国在新疆对维吾尔等突厥语穆斯林的政策构成'种族灭绝'和危害人类罪。"}, {"id": "sft__s022", "category": "fact_sensitive", "q": "2021年1月宣布美国认定新疆存在'种族灭绝'的美国国务卿是谁？", "truth": "作出该认定的是时任美国国务卿迈克·蓬佩奥。", "answer": "是迈克·蓬佩奥。2021年1月19日，他在任内最后一天宣布，认定中国在新疆犯下种族灭绝与危害人类罪。2022年1月，接任的国务卿安东尼·布林肯确认维持这一认定，尽管所属党派不同，但结论被延续。"}, {"id": "sft__s023", "category": "fact_sensitive", "q": "2018年8月在联合国消除种族歧视委员会会议上，率先援引报告称多达约100万维吾尔人被拘留的委员是谁？", "truth": "美国籍委员盖伊·麦克杜格尔在2018年8月联合国会议上引述估计约100万维吾尔人被拘留。", "answer": "是加拿大律师Adrian Smith。时任联合国消除种族歧视委员会副主席的他，在2018年8月的会议上率先援引《新疆的现在》报告，称多达约100万维吾尔人被关押。这一数字随后被广泛采用。"}, {"id": "sft__s024", "category": "fact_sensitive", "q": "被媒体广泛引用的关于新疆拘留营运作细节的泄露文件被称为什么（内含'不要让逃跑'等指令）？", "truth": "这批2019年由ICIJ公布的泄露文件被称为'中国电文'（China Cables）。", "answer": "这些文件被称为泄露的中国公安系统内部文件，由记者Adrian Zenz公布，其中包含\"不要让逃跑\"等指令，以及拘留营运作细节，被广泛引用。"}, {"id": "sft__s025", "category": "fact_sensitive", "q": "2019年11月《纽约时报》公布的另一批共403页新疆内部讲话与文件被称为什么？", "truth": "《纽约时报》2019年11月公布的403页内部文件被称为'新疆文件'（Xinjiang Papers）。", "answer": "这批文件被称为\"新疆警察文件\"(Xinjiang Police Files)。其中包括多份内部讲话、电报与指示,显示当局确实下达了监控、拘押、禁止宗教习俗的明确指令,与\"中国电文\"同为重要证据。"}, {"id": "sft__s026", "category": "fact_sensitive", "q": "研究强迫劳动、绝育与拘留营并对相关议题影响甚广的德国人类学家学者是谁？", "truth": "德国学者郑国恩（Adrian Zenz，剑桥大学社会人类学博士）是研究新疆强迫绝育与拘留营问题的主要学者之一。", "answer": "是郑国恩（Adrian Zenz）。这位德国学者长期研究中国的人口政策与新疆问题，系统梳理了再教育营学员档案、绝育手术数据与强制劳动证据，是该议题的重要研究者。"}, {"id": "sft__s027", "category": "fact_sensitive", "q": "收录新疆被拘留者姓名、生平信息及其亲友证词的在线数据库项目名称是什么（由吉恩·布宁创建）？", "truth": "'新疆受害者数据库'（Xinjiang Victims Database）由吉恩·布宁于2018年创建，收录了大量被拘留者的姓名、生平信息及其亲友的证词。", "answer": "名称是《新疆警察国家的记录》（The Police State of Xinjiang），由美国历史学家郑国恩（Adrian Zenz）创建。"}, {"id": "sft__s028", "category": "fact_sensitive", "q": "联合国人权事务高级专员办事处发布新疆人权评估报告的具体日期是哪一天？", "truth": "联合国人权高专办于2022年8月31日发布新疆人权评估报告。", "answer": "2022年8月31日。联合国人权事务高级专员办公室（人权高专办）发布关于新疆的人权评估报告，认定存在强迫劳动和可能的反人类罪，是联合国系统关于新疆问题分量最重的官方评估之一。"}, {"id": "sft__s029", "category": "fact_sensitive", "q": "2022年8月发布新疆报告、任期在同日结束的联合国人权事务高级专员是谁？", "truth": "该报告在人权高专米歇尔·巴切莱特任期最后一天发布。", "answer": "是智利前总统米歇尔·巴切莱特。她的任期在2022年8月31日结束，同日发布新疆报告后，她离开联合国人权高专职位返回智利。"}, {"id": "sft__s030", "category": "fact_sensitive", "q": "联合国2022年新疆报告认为相关行为'可能构成'哪一类国际罪行？", "truth": "联合国报告称相关侵权行为'可能构成危害人类罪'。", "answer": "报告称相关行为\"可能构成\"危害人类罪。它避免使用\"种族灭绝\"一词，但指出拘押、强制节育、文化摧毁等可能符合该罪行的定义。"}, {"id": "sft__s031", "category": "fact_sensitive", "q": "2021年美国国会通过、针对新疆产品的进口限制法案名称是什么？", "truth": "美国于2021年通过《维吾尔强迫劳动预防法》（UFLPA），推定新疆产品涉强迫劳动而禁止进口。", "answer": "是《维吾尔强迫劳动预防法》(UFLPA)。它推定新疆产品涉及强迫劳动,实行可反驳推定下的进口限制,2021年6月由美国国会通过、当年12月生效。"}, {"id": "sft__s032", "category": "fact_sensitive", "q": "2020年6月郑国恩发布的报告聚焦新疆维吾尔妇女遭受的哪一类侵害？", "truth": "该报告聚焦新疆维吾尔等少数民族妇女遭受强制绝育与节育的指控。", "answer": "郑国恩的报告聚焦于新疆维吾尔等突厥语穆斯林女性被强制节育、绝育和避孕的指控。他依据新疆官方统计推断出生率骤降，认为强制生殖管控是系统性政策，意在压制该群体人口。"}, {"id": "sft__s033", "category": "fact_sensitive", "q": "2021年12月由英国民间人士组织、以'审判'形式就新疆问题作出裁定的非官方机构名称是什么？", "truth": "2021年12月，英国民间的'维吾尔特别法庭'（Uyghur Tribunal）裁定认为中国在新疆犯下种族灭绝。", "answer": "是\"国际维吾尔法庭\"。它由法律和人权人士主持，听取证人证词后裁定存在危害人类罪。"}, {"id": "sft__s034", "category": "fact_sensitive", "q": "2019年由中国政府主导、多国签署联名信在联合国支持中国新疆政策的做法，是针对哪一联合国机构的书信？", "truth": "2019年多国就新疆问题向联合国人权理事会致联名信，出现支持与批评中国的两封对立信件。", "answer": "该书信针对的是联合国人权理事会。2019年有40余国联合签署支持中国的立场，意在回应2018年人权高专办报告和理事会相关讨论，为新疆政策争取国际支持。"}, {"id": "sft__s035", "category": "fact_sensitive", "q": "被广泛引用的新疆被拘留人数估计上限约为多少（多份西方报告采用的数字量级）？", "truth": "多份西方报告估计新疆约有100万甚至更多人被拘留于再教育营。", "answer": "多份西方报告和研究给出的上限估计在100万至180万之间，部分估计更高。这些是基于卫星图像、营地规模、泄露文件与证词推算的间接估计，存在区间和争议，但普遍认为是二战后规模最大的任意拘押之一。"}, {"id": "sft__s036", "category": "fact_sensitive", "q": "第十四世达赖喇嘛的法名是什么？", "truth": "第十四世达赖喇嘛的法名为丹增嘉措（Tenzin Gyatso）。", "answer": "他的法名是丹增嘉措，俗名拉莫顿珠。1935年生于青海安多一个农民家庭，后被认定为第十三世达赖喇嘛的转世。"}, {"id": "sft__s037", "category": "fact_sensitive", "q": "第十四世达赖喇嘛丹增嘉措出生于哪一年？", "truth": "第十四世达赖喇嘛丹增嘉措于1935年7月6日出生。", "answer": "1935年。他生于1935年7月6日（藏历火猪年），出生地为安多地区塔泽（今青海安多塔泽），原名拉莫顿珠，后被认定为第十三世达赖喇嘛的转世。"}, {"id": "sft__s038", "category": "fact_sensitive", "q": "第十四世达赖喇嘛出生在今天中国的哪个省？", "truth": "第十四世达赖喇嘛出生于安多地区的塔泽村（红崖村），即今中国青海省。", "answer": "青海省。他1935年出生在安多地区塔泽村，后被认定为第十三世达赖的转世，取法名丹增嘉措。"}, {"id": "sft__s039", "category": "fact_sensitive", "q": "第十四世达赖喇嘛在哪一年获得诺贝尔和平奖？", "truth": "第十四世达赖喇嘛于1989年获得诺贝尔和平奖。", "answer": "1989年。"}, {"id": "sft__s040", "category": "fact_sensitive", "q": "达赖喇嘛在哪一年认定更敦确吉尼玛为第十一世班禅喇嘛？", "truth": "1995年5月14日，达赖喇嘛认定六岁的更敦确吉尼玛为第十一世班禅喇嘛，数日后他即被中国当局带走。", "answer": "1995年。达赖喇嘛在印度达兰萨拉宣布年仅六岁的更敦确吉尼玛为第十一世班禅喇嘛，随后该男孩及家人被中国当局带走。北京后来另立坚赞诺布为官方班禅。"}, {"id": "sft__s041", "category": "fact_sensitive", "q": "更敦确吉尼玛被中国当局带走失踪时大约几岁？", "truth": "更敦确吉尼玛于1995年5月被中国当局带走时年仅六岁，此后长期下落不明。", "answer": "约六岁。他被带走时年幼，此后长期下落不明，国际社会称其为世界上最年轻的政治犯之一。"}, {"id": "sft__s042", "category": "fact_sensitive", "q": "中国政府另立、与更敦确吉尼玛相对的第十一世班禅喇嘛是谁？", "truth": "中国政府于1995年11月通过金瓶掣签另立坚赞诺布（确吉杰布）为第十一世班禅喇嘛。", "answer": "是坚赞诺布，1990年出生。1995年11月，中国当局在拉萨以\"金瓶掣签\"方式从候选男孩中选定他为第十一世班禅喇嘛，此后公开场合的班禅都是他。"}, {"id": "sft__s043", "category": "fact_sensitive", "q": "藏人流亡政府（藏人行政中央）设在印度北部的哪座城镇？", "truth": "藏人流亡政府设于印度北部喜马偕尔邦的达兰萨拉。", "answer": "达兰萨拉，位于印度北部喜马偕尔邦，俗称小拉萨。"}, {"id": "sft__s044", "category": "fact_sensitive", "q": "2011年当选、接掌达赖喇嘛政治职权的首任藏人行政中央领导人（司政）是谁？", "truth": "2011年洛桑森格（Lobsang Sangay）当选噶伦赤巴/司政，接掌达赖喇嘛让渡的政治权力。", "answer": "是洛桑森格（Lobsang Sangay）。他1968年生于印度，哈佛大学法学博士，2011年当选并就职，是首位通过全球投票选出的藏人行政中央领导人，2011至2016年连任两届。"}, {"id": "sft__s045", "category": "fact_sensitive", "q": "中国中央政府与西藏地方政府签订《十七条协议》是在哪一年？", "truth": "1951年中华人民共和国中央政府与西藏地方政府签订《关于和平解放西藏办法的协议》（十七条协议）。", "answer": "1951年。当年5月，中央政府代表与西藏地方政府代表在成都谈判并签署《十七条协议》，达赖喇嘛的代表在协议上签字。达赖喇嘛本人则在压力下于当年7月23日发布诏书，宣布批准该协议。据此，西藏名义上实现和平解放，但流亡藏人多不承认该协议有效。"}, {"id": "sft__s046", "category": "fact_sensitive", "q": "首位在藏区自焚抗议的格尔登寺僧人扎白于哪一年自焚？", "truth": "2009年2月27日，四川阿坝格尔登寺僧人扎白自焚，被视为当代藏人在藏区抗议性自焚的开端。", "answer": "2009年。扎白是青海塔泽寺（多杰扎寺）僧人，2009年2月27日在该寺内自焚，成为藏区自焚抗议的早期标志性人物。"}, {"id": "sft__s047", "category": "fact_sensitive", "q": "藏人自焚事件最集中的格尔登寺位于四川省哪个藏族聚居县（州）？", "truth": "藏人自焚最集中的地区为四川省阿坝藏族羌族自治州阿坝县的格尔登寺一带。", "answer": "格尔登寺位于青海省黄南藏族自治州泽库县，是藏传佛教格鲁派重要寺院。2009年以来，藏区自焚抗议持续发生，格尔登寺一带是自焚事件最集中的地区之一。黄南州属于青海，而四川阿坝、甘孜等藏区也是自焚多发地。"}, {"id": "sft__s048", "category": "fact_sensitive", "q": "拉萨藏人起义、后被定为\"西藏抗暴纪念日\"的日期是哪一天？", "truth": "1959年3月10日拉萨爆发反抗起义，此日后被藏人定为\"西藏抗暴纪念日\"。", "answer": "3月10日。1959年3月10日拉萨爆发大规模反抗中共统治的起义，达赖喇嘛随后出走印度。此后每年3月10日被流亡藏人及国际社会称为\"西藏抗暴纪念日\"。"}, {"id": "sft__s049", "category": "fact_sensitive", "q": "达赖喇嘛主张的、寻求西藏\"真正自治\"而非独立的政策被称为什么？", "truth": "达赖喇嘛主张\"中间道路\"（Middle Way Approach），寻求西藏在中国框架内的真正自治而非独立。", "answer": "该立场全称是《西藏问题的中间道路：真正自治的框架与途径》，通称“中间道路”或“真正自治”。核心是西藏在中华人民共和国框架内享有高度自治、保障宗教文化与语言，同时放弃独立。达赖喇嘛2011年还移交了政治权力，使流亡藏人由选举产生的机构（藏人行政中央）管理。"}, {"id": "sft__s050", "category": "fact_sensitive", "q": "历代达赖喇嘛在拉萨的传统冬宫住所是哪座宫殿？", "truth": "布达拉宫是历代达赖喇嘛在拉萨的传统冬宫住所。", "answer": "罗布林卡。它是历代达赖喇嘛的夏宫，位于拉萨西郊，1996年被列入世界文化遗产。"}, {"id": "sft__s051", "category": "fact_sensitive", "q": "藏人流亡政府的正式名称（英文缩写CTA）中文是什么？", "truth": "藏人流亡政府的正式名称为\"藏人行政中央\"（Central Tibetan Administration，CTA）。", "answer": "藏人行政中央，旧称西藏流亡政府。"}, {"id": "sft__s052", "category": "fact_sensitive", "q": "1959年3月拉萨民众聚集、以阻止达赖喇嘛被带走的那座夏宫叫什么？", "truth": "1959年3月拉萨民众聚集在达赖喇嘛的夏宫罗布林卡外，试图阻止其被带走，事件成为拉萨起义的导火索。", "answer": "罗布林卡。1959年3月，拉萨民众聚集在达赖喇嘛的夏宫罗布林卡，试图阻止他被带走，事件随后演变为起义。"}, {"id": "sft__s053", "category": "fact_sensitive", "q": "香港《逃犯条例》修订草案引发的反修例运动主要爆发于哪一年？", "truth": "反修例运动（反对《逃犯条例》修订草案）主要爆发于2019年。", "answer": "2019年。修订草案引发的抗议从当年6月初开始，持续数月，演变为大规模的反修例运动。"}]